{
	"configurations" : 
	[
		{
			"directories" : 
			[
				{
					"build" : ".",
					"jsonFile" : "directory-.-Debug-d0094a50bb2071803777.json",
					"minimumCMakeVersion" : 
					{
						"string" : "3.21"
					},
					"projectIndex" : 0,
					"source" : ".",
					"targetIndexes" : 
					[
						0
					]
				}
			],
			"name" : "Debug",
			"projects" : 
			[
				{
					"directoryIndexes" : 
					[
						0
					],
					"name" : "untitled1",
					"targetIndexes" : 
					[
						0
					]
				}
			],
			"targets" : 
			[
				{
					"directoryIndex" : 0,
					"id" : "untitled1.elf::@6890427a1f51a3e7e1df",
					"jsonFile" : "target-untitled1.elf-Debug-097c9cd68f5abce56e4e.json",
					"name" : "untitled1.elf",
					"projectIndex" : 0
				}
			]
		}
	],
	"kind" : "codemodel",
	"paths" : 
	{
		"build" : "D:/Project/MyProject1/mkrtos-gcc/cmake-build-debug",
		"source" : "D:/Project/MyProject1/mkrtos-gcc"
	},
	"version" : 
	{
		"major" : 2,
		"minor" : 3
	}
}
